porkbundns/main.py
porkbundns/dns/__init__.py
porkbundns/dns/dns_types.py
porkbundns/dns/manage_records.py
porkbundns-0.0.1.dist-info/METADATA
porkbundns-0.0.1.dist-info/WHEEL
porkbundns-0.0.1.dist-info/licenses/LICENSE
porkbundns-0.0.1.dist-info/RECORD
