Metadata-Version: 2.1
Name: porkbundns
Version: 0.0.1
Summary: Update DNS records for Porkbun
Project-URL: Homepage, https://github.com/ispmarin/porkbundns
Project-URL: Bug Tracker, https://github.com/ispmarin/porkbundns/issues
Author-email: Ivan Marin <ivan@tunguska.cc>
License: MIT License
Classifier: License :: OSI Approved :: MIT License
Classifier: Operating System :: OS Independent
Classifier: Programming Language :: Python :: 3
Requires-Python: >=3.7
